speedlib/__init__.py
speedlib/cranes/__init__.py
speedlib/cranes/faller.py
speedlib/cranes/gripper.py
speedlib_dedo_fabrice-2.0.dist-info/LICENSE.md
speedlib_dedo_fabrice-2.0.dist-info/METADATA
speedlib_dedo_fabrice-2.0.dist-info/WHEEL
speedlib_dedo_fabrice-2.0.dist-info/top_level.txt
speedlib_dedo_fabrice-2.0.dist-info/RECORD
