Metadata-Version: 2.1
Name: speedlib-dedo-fabrice
Version: 2.0
Summary: A python library to operate 'Speed' devices
Home-page: https://github.com/CRIStAL-PADR/Speed
Author: Fabrice Dedo & Damien Marchal
Author-email: komla-sam-fabrice.dedo@polytech-lille.net
License: UNKNOWN
Platform: UNKNOWN
Classifier: Programming Language :: Python :: 3
Classifier: License :: OSI Approved :: MIT License
Classifier: Operating System :: OS Independent
Requires-Python: >=3.6
